Metadata-Version: 2.1
Name: odoo-addon-graphql_demo
Version: 17.0.1.0.1.2
Requires-Python: >=3.10
Requires-Dist: odoo-addon-graphql_base>=17.0dev,<17.1dev
Requires-Dist: odoo>=17.0a,<17.1dev
Summary: GraphQL Demo
Home-page: https://github.com/OCA/rest-framework
License: LGPL-3
Author: ACSONE SA/NV, Odoo Community Association (OCA)
Author-email: support@odoo-community.org
Classifier: Programming Language :: Python
Classifier: Framework :: Odoo
Classifier: Framework :: Odoo :: 17.0
Classifier: License :: OSI Approved :: GNU Lesser General Public License v3 (LGPLv3)
Classifier: Development Status :: 4 - Beta
